bbcode
bbcode_test
