Metadata-Version: 1.1
Name: mde-bbcode
Version: 4.314159
Summary: Klappfallscheibes BBCode Parser v4 auf Python 3 portiert
Home-page: http://stuff.oorgle.de/bbcode/v4.html
Author: enkore
Author-email: public+mde_bbcode@enkore.de
License: UNKNOWN
Platform: UNKNOWN
Classifier: Development Status :: 4 - Beta
Classifier: Programming Language :: Python :: 3
